{
  "$schema": "https://shippie.app/schemas/app.json",
  "name": "Drift",
  "slug": "drift",
  "description": "Vector-style asteroid shooter. Rotate, thrust, fire, hyperspace. Daily-seed waves, synthwave skin.",
  "icon": "/icon.svg",
  "theme_color": "#15131F",
  "background_color": "#15131F",
  "display": "standalone",
  "orientation": "portrait",
  "intents": {
    "provides": [
      "game.completed"
    ],
    "consumes": []
  },
  "curation": {
    "surface": "archived",
    "category": "games",
    "subcategory": "arcade-cabinet"
  },
  "source_repo": "https://github.com/theprovider123/shippie/tree/main/apps/showcase-drift",
  "license": "AGPL-3.0-or-later",
  "remix_allowed": true
}
